{"type":"FeatureCollection","properties":{"name":"28"},"features":[{"type":"Feature","properties":{"id":"StopPoint:PIRA1","name":"Pirmil"},"geometry":{"type":"Point","coordinates":["-1.54211571","47.19661196"]}},{"type":"Feature","properties":{"id":"StopPoint:GNRA6","name":"Gréneraie"},"geometry":{"type":"Point","coordinates":["-1.53288980","47.19931797"]}},{"type":"Feature","properties":{"id":"StopPoint:MTLI1","name":"Martellière"},"geometry":{"type":"Point","coordinates":["-1.52494132","47.19904426"]}},{"type":"Feature","properties":{"id":"StopPoint:PLAC1","name":"Placis"},"geometry":{"type":"Point","coordinates":["-1.51996778","47.19952609"]}},{"type":"Feature","properties":{"id":"StopPoint:MMSS1","name":"Mermoz"},"geometry":{"type":"Point","coordinates":["-1.51554697","47.19869228"]}},{"type":"Feature","properties":{"id":"StopPoint:LAGE4","name":"Largeau"},"geometry":{"type":"Point","coordinates":["-1.51003708","47.19502161"]}},{"type":"Feature","properties":{"id":"StopPoint:ECBU2","name":"Ecobuts"},"geometry":{"type":"Point","coordinates":["-1.50762196","47.19395841"]}},{"type":"Feature","properties":{"id":"StopPoint:LPME2","name":"La Plume"},"geometry":{"type":"Point","coordinates":["-1.50523405","47.19492971"]}},{"type":"Feature","properties":{"id":"StopPoint:OQNE2","name":"Ouche Quinet"},"geometry":{"type":"Point","coordinates":["-1.50462275","47.19598583"]}},{"type":"Feature","properties":{"id":"StopPoint:RBRN2","name":"René Bernier"},"geometry":{"type":"Point","coordinates":["-1.49944070","47.19392491"]}},{"type":"Feature","properties":{"id":"StopPoint:GLDE2","name":"Grande Lande"},"geometry":{"type":"Point","coordinates":["-1.49756462","47.19226715"]}},{"type":"Feature","properties":{"id":"StopPoint:FRON4","name":"Frêne Rond"},"geometry":{"type":"Point","coordinates":["-1.49638979","47.19025278"]}},{"type":"Feature","properties":{"id":"StopPoint:VTNN1","name":"Vertonne"},"geometry":{"type":"Point","coordinates":["-1.49432297","47.18703420"]}},{"type":"Feature","properties":{"id":"StopPoint:BNTA1","name":"BN"},"geometry":{"type":"Point","coordinates":["-1.49664053","47.18397598"]}},{"type":"Feature","properties":{"id":"StopPoint:MVA98","name":"Mortier Vannerie"},"geometry":{"type":"Point","coordinates":["-1.49944278","47.18012699"]}},{"type":"Feature","properties":{"id":"StopPoint:PVT98","name":"Porte de Vertou"},"geometry":{"type":"Point","coordinates":["-1.50569459","47.18109843"]}},{"type":"Feature","properties":{"id":"StopPoint:PVTO3","name":"Porte de Vertou"},"geometry":{"type":"Point","coordinates":["-1.50458524","47.18055002"]}},{"type":"Feature","properties":{"id":"StopPoint:MVAN1","name":"Mortier Vannerie"},"geometry":{"type":"Point","coordinates":["-1.49939552","47.18002049"]}},{"type":"Feature","properties":{"id":"StopPoint:TMET1","name":"Trois Métairies"},"geometry":{"type":"Point","coordinates":["-1.50164814","47.17643292"]}},{"type":"Feature","properties":{"id":"StopPoint:PTYY1","name":"Planty"},"geometry":{"type":"Point","coordinates":["-1.49489589","47.17528879"]}},{"type":"Feature","properties":{"id":"StopPoint:FRCH1","name":"Fraîches"},"geometry":{"type":"Point","coordinates":["-1.48945289","47.17453309"]}},{"type":"Feature","properties":{"id":"StopPoint:VIVI1","name":"Viviers"},"geometry":{"type":"Point","coordinates":["-1.48491068","47.17307177"]}},{"type":"Feature","properties":{"id":"StopPoint:EUVE1","name":"Europe"},"geometry":{"type":"Point","coordinates":["-1.47631033","47.17304164"]}},{"type":"Feature","properties":{"id":"StopPoint:HMVE1","name":"8 Mai"},"geometry":{"type":"Point","coordinates":["-1.47240317","47.17270262"]}},{"type":"Feature","properties":{"id":"StopPoint:CBGE1","name":"Chapeau Berger"},"geometry":{"type":"Point","coordinates":["-1.46878240","47.17100306"]}},{"type":"Feature","properties":{"id":"StopPoint:VTOU1","name":"Vertou"},"geometry":{"type":"Point","coordinates":["-1.47124887","47.16947150"]}},{"type":"Feature","properties":{"id":"StopPoint:VTOU2","name":"Vertou"},"geometry":{"type":"Point","coordinates":["-1.47108173","47.16879255"]}},{"type":"Feature","properties":{"id":"StopPoint:IDFR1","name":"Ile de France"},"geometry":{"type":"Point","coordinates":["-1.46792834","47.16939213"]}},{"type":"Feature","properties":{"id":"StopPoint:CBGE2","name":"Chapeau Berger"},"geometry":{"type":"Point","coordinates":["-1.46882965","47.17166796"]}},{"type":"Feature","properties":{"id":"StopPoint:HMVE2","name":"8 Mai"},"geometry":{"type":"Point","coordinates":["-1.47243719","47.17280957"]}},{"type":"Feature","properties":{"id":"StopPoint:EUVE2","name":"Europe"},"geometry":{"type":"Point","coordinates":["-1.47650990","47.17306205"]}},{"type":"Feature","properties":{"id":"StopPoint:VIVI2","name":"Viviers"},"geometry":{"type":"Point","coordinates":["-1.48513368","47.17323549"]}},{"type":"Feature","properties":{"id":"StopPoint:FRCH2","name":"Fraîches"},"geometry":{"type":"Point","coordinates":["-1.49053144","47.17483950"]}},{"type":"Feature","properties":{"id":"StopPoint:PTYY2","name":"Planty"},"geometry":{"type":"Point","coordinates":["-1.49532334","47.17535562"]}},{"type":"Feature","properties":{"id":"StopPoint:TMET2","name":"Trois Métairies"},"geometry":{"type":"Point","coordinates":["-1.50203127","47.17661829"]}},{"type":"Feature","properties":{"id":"StopPoint:MVAN2","name":"Mortier Vannerie"},"geometry":{"type":"Point","coordinates":["-1.49944342","47.18013598"]}},{"type":"Feature","properties":{"id":"StopPoint:PVTO4","name":"Porte de Vertou"},"geometry":{"type":"Point","coordinates":["-1.50456082","47.18057785"]}},{"type":"Feature","properties":{"id":"StopPoint:PVT99","name":"Porte de Vertou"},"geometry":{"type":"Point","coordinates":["-1.50457271","47.18055944"]}},{"type":"Feature","properties":{"id":"StopPoint:MVA99","name":"Mortier Vannerie"},"geometry":{"type":"Point","coordinates":["-1.49943505","47.18001917"]}},{"type":"Feature","properties":{"id":"StopPoint:BNTA2","name":"BN"},"geometry":{"type":"Point","coordinates":["-1.49639563","47.18461458"]}},{"type":"Feature","properties":{"id":"StopPoint:VTNN2","name":"Vertonne"},"geometry":{"type":"Point","coordinates":["-1.49393046","47.18653389"]}},{"type":"Feature","properties":{"id":"StopPoint:FRON3","name":"Frêne Rond"},"geometry":{"type":"Point","coordinates":["-1.49643705","47.19035929"]}},{"type":"Feature","properties":{"id":"StopPoint:GLDE1","name":"Grande Lande"},"geometry":{"type":"Point","coordinates":["-1.49775335","47.19250404"]}},{"type":"Feature","properties":{"id":"StopPoint:RBRN1","name":"René Bernier"},"geometry":{"type":"Point","coordinates":["-1.49921468","47.19390542"]}},{"type":"Feature","properties":{"id":"StopPoint:OQNE1","name":"Ouche Quinet"},"geometry":{"type":"Point","coordinates":["-1.50445461","47.19603647"]}},{"type":"Feature","properties":{"id":"StopPoint:LPME1","name":"La Plume"},"geometry":{"type":"Point","coordinates":["-1.50544367","47.19490470"]}},{"type":"Feature","properties":{"id":"StopPoint:ECBU1","name":"Ecobuts"},"geometry":{"type":"Point","coordinates":["-1.50779138","47.19392574"]}},{"type":"Feature","properties":{"id":"StopPoint:LAGE3","name":"Largeau"},"geometry":{"type":"Point","coordinates":["-1.51083585","47.19547228"]}},{"type":"Feature","properties":{"id":"StopPoint:MMSS2","name":"Mermoz"},"geometry":{"type":"Point","coordinates":["-1.51548752","47.19878433"]}},{"type":"Feature","properties":{"id":"StopPoint:PLAC2","name":"Placis"},"geometry":{"type":"Point","coordinates":["-1.52013244","47.19961064"]}},{"type":"Feature","properties":{"id":"StopPoint:MTLI2","name":"Martellière"},"geometry":{"type":"Point","coordinates":["-1.52645646","47.19916459"]}},{"type":"Feature","properties":{"id":"StopPoint:GNRA5","name":"Gréneraie"},"geometry":{"type":"Point","coordinates":["-1.53299053","47.19943167"]}},{"type":"Feature","properties":{"id":"StopPoint:CHTE2","name":"Chatelets"},"geometry":{"type":"Point","coordinates":["-1.54058482","47.19718588"]}},{"type":"Feature","properties":{"id":"StopPoint:PIRD1","name":"Pirmil"},"geometry":{"type":"Point","coordinates":["-1.54259464","47.19610948"]}},{"type":"Feature","properties":{"id":"StopPoint:SBAI1","name":"St-Blaise"},"geometry":{"type":"Point","coordinates":["-1.46898534","47.16716867"]}},{"type":"Feature","properties":{"id":"StopPoint:JMON1","name":"Jean Monnet"},"geometry":{"type":"Point","coordinates":["-1.46519594","47.16624912"]}},{"type":"Feature","properties":{"id":"StopPoint:BRET1","name":"Bretonnière"},"geometry":{"type":"Point","coordinates":["-1.46288734","47.16646943"]}},{"type":"Feature","properties":{"id":"StopPoint:HFVE1","name":"Haute Forêt"},"geometry":{"type":"Point","coordinates":["-1.46560425","47.16828007"]}},{"type":"Feature","properties":{"id":"StopPoint:CBG99","name":"Chapeau Berger"},"geometry":{"type":"Point","coordinates":["-1.46878240","47.17100306"]}},{"type":"Feature","properties":{"id":"StopPoint:SBA99","name":"St-Blaise"},"geometry":{"type":"Point","coordinates":["-1.46909649","47.16724605"]}},{"type":"Feature","properties":{"id":"StopPoint:JMO99","name":"Jean Monnet"},"geometry":{"type":"Point","coordinates":["-1.46514196","47.16623289"]}},{"type":"Feature","properties":{"id":"StopPoint:BRE99","name":"Bretonnière"},"geometry":{"type":"Point","coordinates":["-1.46288670","47.16646044"]}},{"type":"Feature","properties":{"id":"StopPoint:HFV99","name":"Haute Forêt"},"geometry":{"type":"Point","coordinates":["-1.46561870","47.16829760"]}}]}